msg2fastdds/.DS_Store
msg2fastdds/__init__.py
msg2fastdds/rosidl_adapter/__init__.py
msg2fastdds/rosidl_adapter/__main__.py
msg2fastdds/rosidl_adapter/cli.py
msg2fastdds/rosidl_adapter/main.py
msg2fastdds/rosidl_adapter/parser.py
msg2fastdds/rosidl_adapter/action/__init__.py
msg2fastdds/rosidl_adapter/msg/__init__.py
msg2fastdds/rosidl_adapter/resource/__init__.py
msg2fastdds/rosidl_adapter/resource/action.idl.em
msg2fastdds/rosidl_adapter/resource/msg.idl.em
msg2fastdds/rosidl_adapter/resource/srv.idl.em
msg2fastdds/rosidl_adapter/resource/struct.idl.em
msg2fastdds/rosidl_adapter/srv/__init__.py
msg2fastdds/rosidl_cli/__init__.py
msg2fastdds/rosidl_cli/cli.py
msg2fastdds/rosidl_cli/common.py
msg2fastdds/rosidl_cli/entry_points.py
msg2fastdds/rosidl_cli/extensions.py
msg2fastdds/rosidl_cli/command/__init__.py
msg2fastdds/rosidl_cli/command/helpers.py
msg2fastdds/rosidl_cli/command/generate/__init__.py
msg2fastdds/rosidl_cli/command/generate/api.py
msg2fastdds/rosidl_cli/command/generate/extensions.py
msg2fastdds/rosidl_cli/command/translate/__init__.py
msg2fastdds/rosidl_cli/command/translate/api.py
msg2fastdds/rosidl_cli/command/translate/extensions.py
msg2fastdds-0.0.2.dist-info/METADATA
msg2fastdds-0.0.2.dist-info/WHEEL
msg2fastdds-0.0.2.dist-info/entry_points.txt
msg2fastdds-0.0.2.dist-info/licenses/LICENSE
msg2fastdds-0.0.2.dist-info/RECORD
