Metadata-Version: 2.1
Name: msg2fastdds
Version: 0.0.2
Summary: msg2fastdds
Author-email: Rin Iwai <rin@eyrin.jp>
License-File: LICENSE
Requires-Dist: catkin-pkg
Requires-Dist: empy
Requires-Dist: pyyaml
